paygroove/client.py
paygroove/exception.py
paygroove/config.py
paygroove/cli.py
paygroove/models.py
paygroove/__init__.py
paygroove/connection.py
PayGroove-0.0.1.dist-info/top_level.txt
PayGroove-0.0.1.dist-info/DESCRIPTION.rst
PayGroove-0.0.1.dist-info/WHEEL
PayGroove-0.0.1.dist-info/entry_points.txt
PayGroove-0.0.1.dist-info/metadata.json
PayGroove-0.0.1.dist-info/METADATA
PayGroove-0.0.1.dist-info/RECORD
