Metadata-Version: 2.0
Name: PayGroove
Version: 0.0.1
Summary: Library for accessing the PayGroove WebSocket API.
Home-page: http://www.paygroove.com/
Author: Gerald Kaszuba
Author-email: gerald@paygroove.com
License: UNKNOWN
Platform: UNKNOWN
Requires-Dist: twisted
Requires-Dist: autobahn
Requires-Dist: pyOpenSSL
Requires-Dist: service-identity
Requires-Dist: wheel
